chatdollkit/__init__.py
chatdollkit/app.py
chatdollkit/models.py
chatdollkit/version.py
chatdollkit/controllers/__init__.py
chatdollkit/controllers/fastapi_controller.py
chatdollkit/controllers/flask_controller.py
chatdollkit-0.3.0.dist-info/LICENSE
chatdollkit-0.3.0.dist-info/METADATA
chatdollkit-0.3.0.dist-info/WHEEL
chatdollkit-0.3.0.dist-info/top_level.txt
chatdollkit-0.3.0.dist-info/RECORD
