Metadata-Version: 2.1
Name: chatdollkit
Version: 0.3.0
Summary: SDK to create remote skill server for ChatdollKit.
Home-page: https://github.com/uezo/chatdollkit-server-python
Author: uezo
Author-email: uezo@uezo.net
Maintainer: uezo
Maintainer-email: uezo@uezo.net
License: Apache v2
Platform: UNKNOWN
Classifier: Programming Language :: Python :: 3
Requires-Dist: pydantic
